_exampleSWIG.cp38-win_amd64.pyd
exampleSWIG.py
exampleSWIG-0.1.dist-info/METADATA
exampleSWIG-0.1.dist-info/WHEEL
exampleSWIG-0.1.dist-info/top_level.txt
exampleSWIG-0.1.dist-info/RECORD
